revl.py
revl-0.2.0.dist-info/DESCRIPTION.rst
revl-0.2.0.dist-info/LICENSE.txt
revl-0.2.0.dist-info/METADATA
revl-0.2.0.dist-info/RECORD
revl-0.2.0.dist-info/WHEEL
revl-0.2.0.dist-info/metadata.json
revl-0.2.0.dist-info/top_level.txt
