Metadata-Version: 2.0
Name: revl
Version: 0.2.0
Summary: Helps to benchmark code for Autodesk Maya
Home-page: https://github.com/christophercrouzet/revl
Author: Christopher Crouzet
Author-email: christopher.crouzet@gmail.com
License: MIT
Keywords: Autodesk Maya API benchmark test
Platform: UNKNOWN
Classifier: Development Status :: 4 - Beta
Classifier: Intended Audience :: Developers
Classifier: License :: OSI Approved :: MIT License
Classifier: Programming Language :: Python
Classifier: Programming Language :: Python :: 2
Classifier: Programming Language :: Python :: 2.7
Classifier: Topic :: Software Development :: Libraries :: Python Modules
Classifier: Topic :: Utilities
Provides-Extra: dev
Requires-Dist: coverage; extra == 'dev'
Requires-Dist: sphinx (>=1.3); extra == 'dev'
Provides-Extra: docs
Requires-Dist: sphinx (>=1.3); extra == 'docs'
